<?xml version = \"1.0\"?>
<devices>
    <device>
        <pin>
            1
        </pin>
        <enable>
            1
        </enable>
        <on>
            1
        </on>
        <name>
            deviceno1
        </name>
    </device>
    <device>
        <pin>
            1
        </pin>
        <enable>
            2
        </enable>
        <on>
            3
        </on>
        <name>
            deviceno2
        </name>
    </device>
    <device>
        <pin>
            1
        </pin>
        <enable>
            3
        </enable>
        <on>
            2
        </on>
        <name>
            deviceno3
        </name>
    </device>
    <device>
        <pin>
            1
        </pin>
        <enable>
            1
        </enable>
        <on>
            1
        </on>
        <name>
            deviceno4
        </name>
    </device>
    <device>
        <pin>
            1
        </pin>
        <enable>
            1
        </enable>
        <on>
            1
        </on>
        <name>
            deviceno5
        </name>
    </device>
</devices>